<?xml version="1.0" encoding="utf-8"?>
<edmx:Edmx Version="1.0" xmlns:edmx="http://schemas.microsoft.com/ado/2007/06/edmx" xmlns:m="http://schemas.microsoft.com/ado/2007/08/dataservices/metadata" xmlns:sap="http://www.sap.com/Protocols/SAPData">
    <edmx:Reference Uri="https://57526060-7030-478e-9b03-82a327646030.abap.eu10.hana.ondemand.com/sap/opu/odata/iwfnd/catalogservice;v=2/Vocabularies(TechnicalName='%2FIWBEP%2FVOC_COMMON',Version='0001',SAP__Origin='')/$value" xmlns:edmx="http://docs.oasis-open.org/odata/ns/edmx">
        <edmx:Include Namespace="com.sap.vocabularies.Common.v1" Alias="Common"/>
    </edmx:Reference>
    <edmx:Reference Uri="https://57526060-7030-478e-9b03-82a327646030.abap.eu10.hana.ondemand.com/sap/opu/odata/iwfnd/catalogservice;v=2/Vocabularies(TechnicalName='%2FIWBEP%2FVOC_CAPABILITIES',Version='0001',SAP__Origin='')/$value" xmlns:edmx="http://docs.oasis-open.org/odata/ns/edmx">
        <edmx:Include Namespace="Org.OData.Capabilities.V1" Alias="Capabilities"/>
    </edmx:Reference>
    <edmx:Reference Uri="https://57526060-7030-478e-9b03-82a327646030.abap.eu10.hana.ondemand.com/sap/opu/odata/iwfnd/catalogservice;v=2/Vocabularies(TechnicalName='%2FIWBEP%2FVOC_COMMUNICATION',Version='0001',SAP__Origin='')/$value" xmlns:edmx="http://docs.oasis-open.org/odata/ns/edmx">
        <edmx:Include Namespace="com.sap.vocabularies.Communication.v1" Alias="Communication"/>
    </edmx:Reference>
    <edmx:Reference Uri="https://57526060-7030-478e-9b03-82a327646030.abap.eu10.hana.ondemand.com/sap/opu/odata/iwfnd/catalogservice;v=2/Vocabularies(TechnicalName='%2FIWBEP%2FVOC_AGGREGATION',Version='0001',SAP__Origin='')/$value" xmlns:edmx="http://docs.oasis-open.org/odata/ns/edmx">
        <edmx:Include Namespace="Org.OData.Aggregation.V1" Alias="Aggregation"/>
    </edmx:Reference>
    <edmx:Reference Uri="https://57526060-7030-478e-9b03-82a327646030.abap.eu10.hana.ondemand.com/sap/opu/odata/iwfnd/catalogservice;v=2/Vocabularies(TechnicalName='%2FIWBEP%2FVOC_PERSONALDATA',Version='0001',SAP__Origin='')/$value" xmlns:edmx="http://docs.oasis-open.org/odata/ns/edmx">
        <edmx:Include Namespace="com.sap.vocabularies.PersonalData.v1" Alias="PersonalData"/>
    </edmx:Reference>
    <edmx:Reference Uri="https://57526060-7030-478e-9b03-82a327646030.abap.eu10.hana.ondemand.com/sap/opu/odata/iwfnd/catalogservice;v=2/Vocabularies(TechnicalName='%2FIWBEP%2FVOC_VALIDATION',Version='0001',SAP__Origin='')/$value" xmlns:edmx="http://docs.oasis-open.org/odata/ns/edmx">
        <edmx:Include Namespace="Org.OData.Validation.V1" Alias="Validation"/>
    </edmx:Reference>
    <edmx:Reference Uri="https://57526060-7030-478e-9b03-82a327646030.abap.eu10.hana.ondemand.com/sap/opu/odata/iwfnd/catalogservice;v=2/Vocabularies(TechnicalName='%2FIWBEP%2FVOC_ANALYTICS',Version='0001',SAP__Origin='')/$value" xmlns:edmx="http://docs.oasis-open.org/odata/ns/edmx">
        <edmx:Include Namespace="com.sap.vocabularies.Analytics.v1" Alias="Analytics"/>
    </edmx:Reference>
    <edmx:Reference Uri="https://57526060-7030-478e-9b03-82a327646030.abap.eu10.hana.ondemand.com/sap/opu/odata/iwfnd/catalogservice;v=2/Vocabularies(TechnicalName='%2FIWBEP%2FVOC_MEASURES',Version='0001',SAP__Origin='')/$value" xmlns:edmx="http://docs.oasis-open.org/odata/ns/edmx">
        <edmx:Include Namespace="Org.OData.Measures.V1" Alias="Measures"/>
    </edmx:Reference>
    <edmx:Reference Uri="https://57526060-7030-478e-9b03-82a327646030.abap.eu10.hana.ondemand.com/sap/opu/odata/iwfnd/catalogservice;v=2/Vocabularies(TechnicalName='%2FIWBEP%2FVOC_UI',Version='0001',SAP__Origin='')/$value" xmlns:edmx="http://docs.oasis-open.org/odata/ns/edmx">
        <edmx:Include Namespace="com.sap.vocabularies.UI.v1" Alias="UI"/>
    </edmx:Reference>
    <edmx:DataServices m:DataServiceVersion="2.0">
        <Schema Namespace="cds_zui_c_travel_m_123" xml:lang="en" sap:schema-version="1" xmlns="http://schemas.microsoft.com/ado/2008/09/edm">
            <EntityType Name="TravelAgencyType" sap:label="Agency View - CDS Data Model" sap:value-list="true" sap:content-version="1">
                <Key>
                    <PropertyRef Name="AgencyID"/>
                </Key>
                <Property Name="AgencyID" Type="Edm.String" Nullable="false" MaxLength="6" sap:display-format="NonNegative" sap:text="Name" sap:label="Agency ID"/>
                <Property Name="Name" Type="Edm.String" MaxLength="80" sap:label="Agency Name"/>
                <Property Name="Street" Type="Edm.String" MaxLength="60" sap:label="Street"/>
                <Property Name="PostalCode" Type="Edm.String" MaxLength="10" sap:display-format="UpperCase" sap:label="Postal Code"/>
                <Property Name="City" Type="Edm.String" MaxLength="40" sap:label="City"/>
                <Property Name="CountryCode" Type="Edm.String" MaxLength="3" sap:display-format="UpperCase" sap:label="Country/Region Key" sap:value-list="standard"/>
                <Property Name="PhoneNumber" Type="Edm.String" MaxLength="30" sap:display-format="UpperCase" sap:label="Phone No."/>
                <Property Name="EMailAddress" Type="Edm.String" MaxLength="256" sap:label="E-Mail Address"/>
                <Property Name="WebAddress" Type="Edm.String" MaxLength="256" sap:label="Web Address"/>
                <NavigationProperty Name="to_Country" Relationship="cds_zui_c_travel_m_123.assoc_7B8A0A23F3148555D7C8E7C453F7928E" FromRole="FromRole_assoc_7B8A0A23F3148555D7C8E7C453F7928E" ToRole="ToRole_assoc_7B8A0A23F3148555D7C8E7C453F7928E"/>
            </EntityType>
            <EntityType Name="AirportType" sap:label="Airport View - CDS Data Model" sap:content-version="1">
                <Key>
                    <PropertyRef Name="AirportID"/>
                </Key>
                <Property Name="AirportID" Type="Edm.String" Nullable="false" MaxLength="3" sap:display-format="UpperCase" sap:text="Name" sap:label="Airport ID"/>
                <Property Name="Name" Type="Edm.String" MaxLength="40" sap:label="Airport Name"/>
                <Property Name="City" Type="Edm.String" MaxLength="40" sap:label="City"/>
                <Property Name="CountryCode" Type="Edm.String" MaxLength="3" sap:display-format="UpperCase" sap:label="Country/Region Key" sap:value-list="standard"/>
                <NavigationProperty Name="to_Country" Relationship="cds_zui_c_travel_m_123.assoc_242F257963249C32506740F0865CF8D8" FromRole="FromRole_assoc_242F257963249C32506740F0865CF8D8" ToRole="ToRole_assoc_242F257963249C32506740F0865CF8D8"/>
            </EntityType>
            <EntityType Name="PassengerType" sap:label="Customer View - CDS Data Model" sap:value-list="true" sap:content-version="1">
                <Key>
                    <PropertyRef Name="CustomerID"/>
                </Key>
                <Property Name="CustomerID" Type="Edm.String" Nullable="false" MaxLength="6" sap:display-format="NonNegative" sap:text="LastName" sap:label="Customer ID"/>
                <Property Name="FirstName" Type="Edm.String" MaxLength="40" sap:label="First Name"/>
                <Property Name="LastName" Type="Edm.String" MaxLength="40" sap:label="Last Name"/>
                <Property Name="Title" Type="Edm.String" MaxLength="10" sap:label="Title"/>
                <Property Name="Street" Type="Edm.String" MaxLength="60" sap:label="Street"/>
                <Property Name="PostalCode" Type="Edm.String" MaxLength="10" sap:display-format="UpperCase" sap:label="Postal Code"/>
                <Property Name="City" Type="Edm.String" MaxLength="40" sap:label="City"/>
                <Property Name="CountryCode" Type="Edm.String" MaxLength="3" sap:display-format="UpperCase" sap:label="Country/Region Key" sap:value-list="standard"/>
                <Property Name="PhoneNumber" Type="Edm.String" MaxLength="30" sap:display-format="UpperCase" sap:label="Phone No."/>
                <Property Name="EMailAddress" Type="Edm.String" MaxLength="256" sap:label="E-Mail Address"/>
                <NavigationProperty Name="to_Country" Relationship="cds_zui_c_travel_m_123.assoc_A981A07E66D2A72CFAAE262689ED505B" FromRole="FromRole_assoc_A981A07E66D2A72CFAAE262689ED505B" ToRole="ToRole_assoc_A981A07E66D2A72CFAAE262689ED505B"/>
            </EntityType>
            <EntityType Name="CountryType" sap:label="Country" sap:content-version="1">
                <Key>
                    <PropertyRef Name="Country"/>
                </Key>
                <Property Name="Country" Type="Edm.String" Nullable="false" MaxLength="3" sap:display-format="UpperCase" sap:text="Country_Text" sap:label="Country/Region Key"/>
                <Property Name="Country_Text" Type="Edm.String" MaxLength="50" sap:label="Country/Region Name" sap:creatable="false" sap:updatable="false"/>
                <Property Name="CountryThreeLetterISOCode" Type="Edm.String" MaxLength="3" sap:display-format="UpperCase" sap:label="ISO Code 3 Char"/>
                <Property Name="CountryThreeDigitISOCode" Type="Edm.String" MaxLength="3" sap:display-format="NonNegative" sap:label="ISO Code Num. 3"/>
                <Property Name="CountryISOCode" Type="Edm.String" MaxLength="2" sap:display-format="UpperCase" sap:label="ISO code"/>
            </EntityType>
            <EntityType Name="CurrencyType" sap:label="Currency" sap:value-list="true" sap:content-version="1">
                <Key>
                    <PropertyRef Name="Currency"/>
                </Key>
                <Property Name="Currency" Type="Edm.String" Nullable="false" MaxLength="5" sap:text="Currency_Text" sap:label="Currency" sap:semantics="currency-code"/>
                <Property Name="Currency_Text" Type="Edm.String" MaxLength="40" sap:label="Description" sap:creatable="false" sap:updatable="false"/>
                <Property Name="Decimals" Type="Edm.Byte" sap:label="Decimal Places"/>
                <Property Name="CurrencyISOCode" Type="Edm.String" MaxLength="3" sap:display-format="UpperCase" sap:label="ISO Code"/>
                <Property Name="AlternativeCurrencyKey" Type="Edm.String" MaxLength="3" sap:display-format="UpperCase" sap:label="Alternative Key"/>
                <Property Name="IsPrimaryCurrencyForISOCrcy" Type="Edm.Boolean" sap:display-format="UpperCase" sap:label="Primary"/>
            </EntityType>
            <EntityType Name="TravelProcessorType" sap:label="Travel projection view - Processor" sap:content-version="1">
                <Key>
                    <PropertyRef Name="TravelUUID"/>
                </Key>
                <Property Name="TravelUUID" Type="Edm.Guid" Nullable="false" sap:label="UUID"/>
                <Property Name="TravelID" Type="Edm.String" MaxLength="8" sap:display-format="NonNegative" sap:label="Travel ID"/>
                <Property Name="AgencyID" Type="Edm.String" MaxLength="6" sap:display-format="NonNegative" sap:text="AgencyName" sap:label="Agency ID" sap:value-list="standard"/>
                <Property Name="AgencyName" Type="Edm.String" MaxLength="80" sap:label="Agency Name"/>
                <Property Name="CustomerID" Type="Edm.String" MaxLength="6" sap:display-format="NonNegative" sap:text="CustomerName" sap:label="Customer ID" sap:value-list="standard"/>
                <Property Name="CustomerName" Type="Edm.String" MaxLength="40" sap:label="Last Name"/>
                <Property Name="BeginDate" Type="Edm.DateTime" Precision="0" sap:display-format="Date" sap:label="Starting Date"/>
                <Property Name="EndDate" Type="Edm.DateTime" Precision="0" sap:display-format="Date" sap:label="End Date"/>
                <Property Name="TotalPrice" Type="Edm.Decimal" Precision="17" Scale="3" sap:unit="CurrencyCode" sap:label="Total Price"/>
                <Property Name="CurrencyCode" Type="Edm.String" MaxLength="5" sap:label="Currency Code" sap:value-list="standard" sap:semantics="currency-code"/>
                <Property Name="TravelStatus" Type="Edm.String" MaxLength="1" sap:display-format="UpperCase" sap:label="Overall Status"/>
                <Property Name="Description" Type="Edm.String" MaxLength="1024" sap:label="Description"/>
                <Property Name="LastChangedAt" Type="Edm.DateTimeOffset" Precision="7" sap:label="Time Stamp"/>
            </EntityType>
            <Association Name="assoc_A981A07E66D2A72CFAAE262689ED505B" sap:content-version="1">
                <End Type="cds_zui_c_travel_m_123.PassengerType" Multiplicity="1" Role="FromRole_assoc_A981A07E66D2A72CFAAE262689ED505B"/>
                <End Type="cds_zui_c_travel_m_123.CountryType" Multiplicity="0..1" Role="ToRole_assoc_A981A07E66D2A72CFAAE262689ED505B"/>
            </Association>
            <Association Name="assoc_242F257963249C32506740F0865CF8D8" sap:content-version="1">
                <End Type="cds_zui_c_travel_m_123.AirportType" Multiplicity="1" Role="FromRole_assoc_242F257963249C32506740F0865CF8D8"/>
                <End Type="cds_zui_c_travel_m_123.CountryType" Multiplicity="0..1" Role="ToRole_assoc_242F257963249C32506740F0865CF8D8"/>
            </Association>
            <Association Name="assoc_7B8A0A23F3148555D7C8E7C453F7928E" sap:content-version="1">
                <End Type="cds_zui_c_travel_m_123.TravelAgencyType" Multiplicity="1" Role="FromRole_assoc_7B8A0A23F3148555D7C8E7C453F7928E"/>
                <End Type="cds_zui_c_travel_m_123.CountryType" Multiplicity="0..1" Role="ToRole_assoc_7B8A0A23F3148555D7C8E7C453F7928E"/>
            </Association>
            <EntityContainer Name="cds_zui_c_travel_m_123_Entities" m:IsDefaultEntityContainer="true" sap:message-scope-supported="true" sap:supported-formats="atom json xlsx">
                <EntitySet Name="TravelAgency" EntityType="cds_zui_c_travel_m_123.TravelAgencyType" sap:creatable="false" sap:updatable="false" sap:deletable="false" sap:searchable="true" sap:content-version="1"/>
                <EntitySet Name="Airport" EntityType="cds_zui_c_travel_m_123.AirportType" sap:creatable="false" sap:updatable="false" sap:deletable="false" sap:searchable="true" sap:content-version="1"/>
                <EntitySet Name="Passenger" EntityType="cds_zui_c_travel_m_123.PassengerType" sap:creatable="false" sap:updatable="false" sap:deletable="false" sap:searchable="true" sap:content-version="1"/>
                <EntitySet Name="Country" EntityType="cds_zui_c_travel_m_123.CountryType" sap:creatable="false" sap:updatable="false" sap:deletable="false" sap:searchable="true" sap:content-version="1"/>
                <EntitySet Name="Currency" EntityType="cds_zui_c_travel_m_123.CurrencyType" sap:creatable="false" sap:updatable="false" sap:deletable="false" sap:searchable="true" sap:content-version="1"/>
                <EntitySet Name="TravelProcessor" EntityType="cds_zui_c_travel_m_123.TravelProcessorType" sap:creatable="false" sap:updatable="false" sap:deletable="false" sap:searchable="true" sap:content-version="1"/>
                <AssociationSet Name="assoc_242F257963249C32506740F0865CF8D8" Association="cds_zui_c_travel_m_123.assoc_242F257963249C32506740F0865CF8D8" sap:creatable="false" sap:updatable="false" sap:deletable="false" sap:content-version="1">
                    <End EntitySet="Airport" Role="FromRole_assoc_242F257963249C32506740F0865CF8D8"/>
                    <End EntitySet="Country" Role="ToRole_assoc_242F257963249C32506740F0865CF8D8"/>
                </AssociationSet>
                <AssociationSet Name="assoc_7B8A0A23F3148555D7C8E7C453F7928E" Association="cds_zui_c_travel_m_123.assoc_7B8A0A23F3148555D7C8E7C453F7928E" sap:creatable="false" sap:updatable="false" sap:deletable="false" sap:content-version="1">
                    <End EntitySet="TravelAgency" Role="FromRole_assoc_7B8A0A23F3148555D7C8E7C453F7928E"/>
                    <End EntitySet="Country" Role="ToRole_assoc_7B8A0A23F3148555D7C8E7C453F7928E"/>
                </AssociationSet>
                <AssociationSet Name="assoc_A981A07E66D2A72CFAAE262689ED505B" Association="cds_zui_c_travel_m_123.assoc_A981A07E66D2A72CFAAE262689ED505B" sap:creatable="false" sap:updatable="false" sap:deletable="false" sap:content-version="1">
                    <End EntitySet="Passenger" Role="FromRole_assoc_A981A07E66D2A72CFAAE262689ED505B"/>
                    <End EntitySet="Country" Role="ToRole_assoc_A981A07E66D2A72CFAAE262689ED505B"/>
                </AssociationSet>
            </EntityContainer>
            <Annotations Target="cds_zui_c_travel_m_123.TravelAgencyType/CountryCode" xmlns="http://docs.oasis-open.org/odata/ns/edm">
                <Annotation Term="Common.ValueList">
                    <Record>
                        <PropertyValue Property="Label" String=""/>
                        <PropertyValue Property="CollectionPath" String="Country"/>
                        <PropertyValue Property="SearchSupported" Bool="true"/>
                        <PropertyValue Property="Parameters">
                            <Collection>
                                <Record Type="Common.ValueListParameterInOut">
                                    <PropertyValue Property="LocalDataProperty" PropertyPath="CountryCode"/>
                                    <PropertyValue Property="ValueListProperty" String="Country"/>
                                </Record>
                                <Record Type="Common.ValueListParameterDisplayOnly">
                                    <PropertyValue Property="ValueListProperty" String="Country_Text"/>
                                </Record>
                                <Record Type="Common.ValueListParameterDisplayOnly">
                                    <PropertyValue Property="ValueListProperty" String="CountryThreeLetterISOCode"/>
                                </Record>
                                <Record Type="Common.ValueListParameterDisplayOnly">
                                    <PropertyValue Property="ValueListProperty" String="CountryThreeDigitISOCode"/>
                                </Record>
                                <Record Type="Common.ValueListParameterDisplayOnly">
                                    <PropertyValue Property="ValueListProperty" String="CountryISOCode"/>
                                </Record>
                            </Collection>
                        </PropertyValue>
                    </Record>
                </Annotation>
            </Annotations>
            <Annotations Target="cds_zui_c_travel_m_123.AirportType/CountryCode" xmlns="http://docs.oasis-open.org/odata/ns/edm">
                <Annotation Term="Common.ValueList">
                    <Record>
                        <PropertyValue Property="Label" String=""/>
                        <PropertyValue Property="CollectionPath" String="Country"/>
                        <PropertyValue Property="SearchSupported" Bool="true"/>
                        <PropertyValue Property="Parameters">
                            <Collection>
                                <Record Type="Common.ValueListParameterInOut">
                                    <PropertyValue Property="LocalDataProperty" PropertyPath="CountryCode"/>
                                    <PropertyValue Property="ValueListProperty" String="country"/>
                                </Record>
                                <Record Type="Common.ValueListParameterDisplayOnly">
                                    <PropertyValue Property="ValueListProperty" String="Country"/>
                                </Record>
                                <Record Type="Common.ValueListParameterDisplayOnly">
                                    <PropertyValue Property="ValueListProperty" String="Country_Text"/>
                                </Record>
                                <Record Type="Common.ValueListParameterDisplayOnly">
                                    <PropertyValue Property="ValueListProperty" String="CountryThreeLetterISOCode"/>
                                </Record>
                                <Record Type="Common.ValueListParameterDisplayOnly">
                                    <PropertyValue Property="ValueListProperty" String="CountryThreeDigitISOCode"/>
                                </Record>
                                <Record Type="Common.ValueListParameterDisplayOnly">
                                    <PropertyValue Property="ValueListProperty" String="CountryISOCode"/>
                                </Record>
                            </Collection>
                        </PropertyValue>
                    </Record>
                </Annotation>
            </Annotations>
            <Annotations Target="cds_zui_c_travel_m_123.PassengerType/CountryCode" xmlns="http://docs.oasis-open.org/odata/ns/edm">
                <Annotation Term="Common.ValueList">
                    <Record>
                        <PropertyValue Property="Label" String=""/>
                        <PropertyValue Property="CollectionPath" String="Country"/>
                        <PropertyValue Property="SearchSupported" Bool="true"/>
                        <PropertyValue Property="Parameters">
                            <Collection>
                                <Record Type="Common.ValueListParameterInOut">
                                    <PropertyValue Property="LocalDataProperty" PropertyPath="CountryCode"/>
                                    <PropertyValue Property="ValueListProperty" String="Country"/>
                                </Record>
                                <Record Type="Common.ValueListParameterDisplayOnly">
                                    <PropertyValue Property="ValueListProperty" String="Country_Text"/>
                                </Record>
                                <Record Type="Common.ValueListParameterDisplayOnly">
                                    <PropertyValue Property="ValueListProperty" String="CountryThreeLetterISOCode"/>
                                </Record>
                                <Record Type="Common.ValueListParameterDisplayOnly">
                                    <PropertyValue Property="ValueListProperty" String="CountryThreeDigitISOCode"/>
                                </Record>
                                <Record Type="Common.ValueListParameterDisplayOnly">
                                    <PropertyValue Property="ValueListProperty" String="CountryISOCode"/>
                                </Record>
                            </Collection>
                        </PropertyValue>
                    </Record>
                </Annotation>
            </Annotations>
            <Annotations Target="cds_zui_c_travel_m_123.TravelProcessorType/AgencyID" xmlns="http://docs.oasis-open.org/odata/ns/edm">
                <Annotation Term="Common.ValueList">
                    <Record>
                        <PropertyValue Property="Label" String=""/>
                        <PropertyValue Property="CollectionPath" String="TravelAgency"/>
                        <PropertyValue Property="SearchSupported" Bool="true"/>
                        <PropertyValue Property="Parameters">
                            <Collection>
                                <Record Type="Common.ValueListParameterInOut">
                                    <PropertyValue Property="LocalDataProperty" PropertyPath="AgencyID"/>
                                    <PropertyValue Property="ValueListProperty" String="AgencyID"/>
                                </Record>
                                <Record Type="Common.ValueListParameterDisplayOnly">
                                    <PropertyValue Property="ValueListProperty" String="Name"/>
                                </Record>
                                <Record Type="Common.ValueListParameterDisplayOnly">
                                    <PropertyValue Property="ValueListProperty" String="Street"/>
                                </Record>
                                <Record Type="Common.ValueListParameterDisplayOnly">
                                    <PropertyValue Property="ValueListProperty" String="PostalCode"/>
                                </Record>
                                <Record Type="Common.ValueListParameterDisplayOnly">
                                    <PropertyValue Property="ValueListProperty" String="City"/>
                                </Record>
                                <Record Type="Common.ValueListParameterDisplayOnly">
                                    <PropertyValue Property="ValueListProperty" String="CountryCode"/>
                                </Record>
                                <Record Type="Common.ValueListParameterDisplayOnly">
                                    <PropertyValue Property="ValueListProperty" String="PhoneNumber"/>
                                </Record>
                                <Record Type="Common.ValueListParameterDisplayOnly">
                                    <PropertyValue Property="ValueListProperty" String="EMailAddress"/>
                                </Record>
                                <Record Type="Common.ValueListParameterDisplayOnly">
                                    <PropertyValue Property="ValueListProperty" String="WebAddress"/>
                                </Record>
                            </Collection>
                        </PropertyValue>
                    </Record>
                </Annotation>
            </Annotations>
            <Annotations Target="cds_zui_c_travel_m_123.TravelProcessorType/CustomerID" xmlns="http://docs.oasis-open.org/odata/ns/edm">
                <Annotation Term="Common.ValueList">
                    <Record>
                        <PropertyValue Property="Label" String=""/>
                        <PropertyValue Property="CollectionPath" String="Passenger"/>
                        <PropertyValue Property="SearchSupported" Bool="true"/>
                        <PropertyValue Property="Parameters">
                            <Collection>
                                <Record Type="Common.ValueListParameterInOut">
                                    <PropertyValue Property="LocalDataProperty" PropertyPath="CustomerID"/>
                                    <PropertyValue Property="ValueListProperty" String="CustomerID"/>
                                </Record>
                                <Record Type="Common.ValueListParameterDisplayOnly">
                                    <PropertyValue Property="ValueListProperty" String="FirstName"/>
                                </Record>
                                <Record Type="Common.ValueListParameterDisplayOnly">
                                    <PropertyValue Property="ValueListProperty" String="LastName"/>
                                </Record>
                                <Record Type="Common.ValueListParameterDisplayOnly">
                                    <PropertyValue Property="ValueListProperty" String="Title"/>
                                </Record>
                                <Record Type="Common.ValueListParameterDisplayOnly">
                                    <PropertyValue Property="ValueListProperty" String="Street"/>
                                </Record>
                                <Record Type="Common.ValueListParameterDisplayOnly">
                                    <PropertyValue Property="ValueListProperty" String="PostalCode"/>
                                </Record>
                                <Record Type="Common.ValueListParameterDisplayOnly">
                                    <PropertyValue Property="ValueListProperty" String="City"/>
                                </Record>
                                <Record Type="Common.ValueListParameterDisplayOnly">
                                    <PropertyValue Property="ValueListProperty" String="CountryCode"/>
                                </Record>
                                <Record Type="Common.ValueListParameterDisplayOnly">
                                    <PropertyValue Property="ValueListProperty" String="PhoneNumber"/>
                                </Record>
                                <Record Type="Common.ValueListParameterDisplayOnly">
                                    <PropertyValue Property="ValueListProperty" String="EMailAddress"/>
                                </Record>
                            </Collection>
                        </PropertyValue>
                    </Record>
                </Annotation>
            </Annotations>
            <Annotations Target="cds_zui_c_travel_m_123.TravelProcessorType/CurrencyCode" xmlns="http://docs.oasis-open.org/odata/ns/edm">
                <Annotation Term="Common.ValueList">
                    <Record>
                        <PropertyValue Property="Label" String=""/>
                        <PropertyValue Property="CollectionPath" String="Currency"/>
                        <PropertyValue Property="SearchSupported" Bool="true"/>
                        <PropertyValue Property="Parameters">
                            <Collection>
                                <Record Type="Common.ValueListParameterInOut">
                                    <PropertyValue Property="LocalDataProperty" PropertyPath="CurrencyCode"/>
                                    <PropertyValue Property="ValueListProperty" String="Currency"/>
                                </Record>
                                <Record Type="Common.ValueListParameterDisplayOnly">
                                    <PropertyValue Property="ValueListProperty" String="Currency_Text"/>
                                </Record>
                                <Record Type="Common.ValueListParameterDisplayOnly">
                                    <PropertyValue Property="ValueListProperty" String="Decimals"/>
                                </Record>
                                <Record Type="Common.ValueListParameterDisplayOnly">
                                    <PropertyValue Property="ValueListProperty" String="CurrencyISOCode"/>
                                </Record>
                                <Record Type="Common.ValueListParameterDisplayOnly">
                                    <PropertyValue Property="ValueListProperty" String="AlternativeCurrencyKey"/>
                                </Record>
                                <Record Type="Common.ValueListParameterDisplayOnly">
                                    <PropertyValue Property="ValueListProperty" String="IsPrimaryCurrencyForISOCrcy"/>
                                </Record>
                            </Collection>
                        </PropertyValue>
                    </Record>
                </Annotation>
            </Annotations>
            <Annotations Target="cds_zui_c_travel_m_123.cds_zui_c_travel_m_123_Entities" xmlns="http://docs.oasis-open.org/odata/ns/edm">
                <Annotation Term="Common.ApplyMultiUnitBehaviorForSortingAndFiltering" Bool="true"/>
                <Annotation Term="Aggregation.ApplySupported">
                    <Record>
                        <PropertyValue Property="Transformations">
                            <Collection>
                                <String>aggregate</String>
                                <String>groupby</String>
                                <String>filter</String>
                            </Collection>
                        </PropertyValue>
                        <PropertyValue Property="Rollup" EnumMember="None"/>
                    </Record>
                </Annotation>
            </Annotations>
            <Annotations Target="cds_zui_c_travel_m_123.cds_zui_c_travel_m_123_Entities/Passenger" xmlns="http://docs.oasis-open.org/odata/ns/edm">
                <Annotation Term="Capabilities.FilterRestrictions">
                    <Record>
                        <PropertyValue Property="FilterExpressionRestrictions">
                            <Collection>
                                <Record>
                                    <PropertyValue Property="Property" PropertyPath="EMailAddress"/>
                                    <PropertyValue Property="AllowedExpressions" String="SearchExpression"/>
                                </Record>
                            </Collection>
                        </PropertyValue>
                    </Record>
                </Annotation>
                <Annotation Term="Capabilities.SortRestrictions">
                    <Record>
                        <PropertyValue Property="NonSortableProperties">
                            <Collection>
                                <PropertyPath>EMailAddress</PropertyPath>
                            </Collection>
                        </PropertyValue>
                    </Record>
                </Annotation>
            </Annotations>
            <Annotations Target="cds_zui_c_travel_m_123.cds_zui_c_travel_m_123_Entities/TravelAgency" xmlns="http://docs.oasis-open.org/odata/ns/edm">
                <Annotation Term="Capabilities.FilterRestrictions">
                    <Record>
                        <PropertyValue Property="FilterExpressionRestrictions">
                            <Collection>
                                <Record>
                                    <PropertyValue Property="Property" PropertyPath="EMailAddress"/>
                                    <PropertyValue Property="AllowedExpressions" String="SearchExpression"/>
                                </Record>
                                <Record>
                                    <PropertyValue Property="Property" PropertyPath="WebAddress"/>
                                    <PropertyValue Property="AllowedExpressions" String="SearchExpression"/>
                                </Record>
                            </Collection>
                        </PropertyValue>
                    </Record>
                </Annotation>
                <Annotation Term="Capabilities.SortRestrictions">
                    <Record>
                        <PropertyValue Property="NonSortableProperties">
                            <Collection>
                                <PropertyPath>EMailAddress</PropertyPath>
                                <PropertyPath>WebAddress</PropertyPath>
                            </Collection>
                        </PropertyValue>
                    </Record>
                </Annotation>
            </Annotations>
            <Annotations Target="cds_zui_c_travel_m_123.CurrencyType/Currency" xmlns="http://docs.oasis-open.org/odata/ns/edm">
                <Annotation Term="Common.UnitSpecificScale" Path="Decimals"/>
            </Annotations>
            <Annotations Target="cds_zui_c_travel_m_123.cds_zui_c_travel_m_123_Entities" xmlns="http://docs.oasis-open.org/odata/ns/edm">
                <Annotation Term="Org.OData.Capabilities.V1.BatchSupport">
                    <Record Type="Org.OData.Capabilities.V1.BatchSupportType">
                        <PropertyValue Property="ReferencesAcrossChangeSetsSupported" Bool="true"/>
                    </Record>
                </Annotation>
            </Annotations>
            <atom:link rel="self" href="https://57526060-7030-478e-9b03-82a327646030.abap.eu10.hana.ondemand.com/sap/opu/odata/sap/ZUI_C_TRAVEL_M_123/$metadata" xmlns:atom="http://www.w3.org/2005/Atom"/>
            <atom:link rel="latest-version" href="https://57526060-7030-478e-9b03-82a327646030.abap.eu10.hana.ondemand.com/sap/opu/odata/sap/ZUI_C_TRAVEL_M_123/$metadata" xmlns:atom="http://www.w3.org/2005/Atom"/>
        </Schema>
    </edmx:DataServices>
</edmx:Edmx>